pi_inference_scheduler/__init__.py
pi_inference_scheduler/env.py
pi_inference_scheduler/server.py
pi_inference_scheduler-0.1.0.dist-info/METADATA
pi_inference_scheduler-0.1.0.dist-info/WHEEL
pi_inference_scheduler-0.1.0.dist-info/entry_points.txt
pi_inference_scheduler-0.1.0.dist-info/RECORD
