Metadata-Version: 2.4
Name: pi-inference-scheduler
Version: 0.1.0
Summary: Prime Inference Scheduler
Author-email: Jackmin801 <ongjackm@gmail.com>
License: MIT
Requires-Python: ~=3.12.0
Requires-Dist: fastapi[standard]
Requires-Dist: setuptools
Requires-Dist: uvicorn[standard]
